pykmsim/__init__.py
pykmsim/__meta__.py
pykmsim/module.py
pykmsim-0.1.0.dist-info/LICENSE
pykmsim-0.1.0.dist-info/METADATA
pykmsim-0.1.0.dist-info/WHEEL
pykmsim-0.1.0.dist-info/top_level.txt
pykmsim-0.1.0.dist-info/RECORD
