Metadata-Version: 2.1
Name: pykmsim
Version: 0.1.0
Summary: This is a python rewrite of kmsim to allow for better maintainbility and usability
Home-page: https://github.com/jrachit10/pykmsim
Author: Rachit Jain
Author-email: rachit.jain@wustl.edu
License: MIT
Classifier: Natural Language :: English
Classifier: Programming Language :: Python
Classifier: Programming Language :: Python :: 3
Classifier: Programming Language :: Python :: 3.6
Classifier: Programming Language :: Python :: 3.7
Classifier: Programming Language :: Python :: 3.8
Classifier: Programming Language :: Python :: 3.9
Classifier: Programming Language :: Python :: 3.10
Requires-Python: >=3.6
License-File: LICENSE
Requires-Dist: numpy
Requires-Dist: scipy
Provides-Extra: all
Requires-Dist: black (==22.3.0) ; extra == 'all'
Requires-Dist: identify (>=1.4.20) ; extra == 'all'
Requires-Dist: myst-parser ; extra == 'all'
Requires-Dist: pre-commit ; extra == 'all'
Requires-Dist: pypandoc (>=1.6.3) ; extra == 'all'
Requires-Dist: pytest ; extra == 'all'
Requires-Dist: pytest-cov ; extra == 'all'
Requires-Dist: pytest-flake8 ; extra == 'all'
Requires-Dist: sphinx-autobuild ; extra == 'all'
Requires-Dist: sphinx-rtd-dark-mode ; extra == 'all'
Requires-Dist: sphinx (>=3.5.4) ; extra == 'all'
Requires-Dist: watchdog (<1.0.0) ; (python_version < "3.6") and extra == 'all'
Requires-Dist: readthedocs-sphinx-search ; (python_version >= "3.6") and extra == 'all'
Provides-Extra: dev
Requires-Dist: black (==22.3.0) ; extra == 'dev'
Requires-Dist: identify (>=1.4.20) ; extra == 'dev'
Requires-Dist: pre-commit ; extra == 'dev'
Provides-Extra: docs
Requires-Dist: myst-parser ; extra == 'docs'
Requires-Dist: pypandoc (>=1.6.3) ; extra == 'docs'
Requires-Dist: sphinx (>=3.5.4) ; extra == 'docs'
Requires-Dist: sphinx-autobuild ; extra == 'docs'
Requires-Dist: sphinx-rtd-dark-mode ; extra == 'docs'
Requires-Dist: watchdog (<1.0.0) ; (python_version < "3.6") and extra == 'docs'
Requires-Dist: readthedocs-sphinx-search ; (python_version >= "3.6") and extra == 'docs'
Provides-Extra: test
Requires-Dist: pytest ; extra == 'test'
Requires-Dist: pytest-cov ; extra == 'test'
Requires-Dist: pytest-flake8 ; extra == 'test'
